mxnet/__init__.py
mxnet/attribute.py
mxnet/autograd.py
mxnet/base.py
mxnet/callback.py
mxnet/context.py
mxnet/engine.py
mxnet/executor.py
mxnet/executor_manager.py
mxnet/initializer.py
mxnet/io.py
mxnet/kvstore.py
mxnet/kvstore_server.py
mxnet/libinfo.py
mxnet/log.py
mxnet/lr_scheduler.py
mxnet/metric.py
mxnet/misc.py
mxnet/model.py
mxnet/monitor.py
mxnet/name.py
mxnet/ndarray_doc.py
mxnet/operator.py
mxnet/optimizer.py
mxnet/profiler.py
mxnet/random.py
mxnet/recordio.py
mxnet/registry.py
mxnet/rtc.py
mxnet/symbol_doc.py
mxnet/test_utils.py
mxnet/torch.py
mxnet/visualization.py
mxnet/_ctypes/__init__.py
mxnet/_ctypes/ndarray.py
mxnet/_ctypes/symbol.py
mxnet/_cy2/__init__.py
mxnet/_cy3/__init__.py
mxnet/contrib/__init__.py
mxnet/contrib/autograd.py
mxnet/contrib/io.py
mxnet/contrib/ndarray.py
mxnet/contrib/quantization.py
mxnet/contrib/symbol.py
mxnet/contrib/tensorboard.py
mxnet/contrib/onnx/__init__.py
mxnet/contrib/onnx/_import/__init__.py
mxnet/contrib/onnx/_import/import_helper.py
mxnet/contrib/onnx/_import/import_model.py
mxnet/contrib/onnx/_import/import_onnx.py
mxnet/contrib/onnx/_import/op_translations.py
mxnet/contrib/onnx/_import/translation_utils.py
mxnet/contrib/text/__init__.py
mxnet/contrib/text/_constants.py
mxnet/contrib/text/embedding.py
mxnet/contrib/text/utils.py
mxnet/contrib/text/vocab.py
mxnet/gluon/__init__.py
mxnet/gluon/block.py
mxnet/gluon/loss.py
mxnet/gluon/parameter.py
mxnet/gluon/trainer.py
mxnet/gluon/utils.py
mxnet/gluon/contrib/__init__.py
mxnet/gluon/contrib/data/__init__.py
mxnet/gluon/contrib/data/_constants.py
mxnet/gluon/contrib/data/sampler.py
mxnet/gluon/contrib/data/text.py
mxnet/gluon/contrib/nn/__init__.py
mxnet/gluon/contrib/nn/basic_layers.py
mxnet/gluon/contrib/rnn/__init__.py
mxnet/gluon/contrib/rnn/conv_rnn_cell.py
mxnet/gluon/contrib/rnn/rnn_cell.py
mxnet/gluon/data/__init__.py
mxnet/gluon/data/dataloader.py
mxnet/gluon/data/dataset.py
mxnet-1.2.1.dist-info/DESCRIPTION.rst
mxnet-1.2.1.dist-info/METADATA
mxnet-1.2.1.dist-info/RECORD
mxnet-1.2.1.dist-info/WHEEL
mxnet-1.2.1.dist-info/metadata.json
mxnet-1.2.1.dist-info/top_level.txt
