Metadata-Version: 2.0
Name: mxnet_jetson
Version: 1.2.1
Summary: MXNet Python Package
Requires-Dist: numpy (<=1.15.0,>=1.8.2)
Requires-Dist: requests (<2.19.0,>=2.18.4)
Requires-Dist: graphviz (<0.9.0,>=0.8.1)
